Workbook

Sheet Inputs
A1: ROC Tax Burden Formula Workbook / ROC 과세부담 수식 내장 엑셀
A3: Input | B3: Value | C3: Unit | D3: Description | F3: Lower Bound | G3: Upper Bound | H3: Rate | I3: Deduction
A4: Starting Asset A0 | B4: 823100000 | C4: KRW | D4: 시작 투자자산 | F4: 0 | G4: 14000000 | H4: 0.06 | I4: 0
A5: Existing Taxable Income | B5: 9000000 | C5: KRW | D5: 기존 과세표준 소득(근로, 사업자 등) | F5: 14000000 | G5: 50000000 | H5: 0.14 | I5: 1260000
A6: Distribution Rate y | B6: 1 | C6: % | D6: 분배율 | F6: 50000000 | G6: 88000000 | H6: 0.24 | I6: 6260000
A7: ROC Ratio r | B7: 0.89 | C7: % | D7: ROC 비중 | F7: 88000000 | G7: 150000000 | H7: 0.35 | I7: 15940000
A8: Asset Growth Rate g | B8: 0 | C8: % | D8: 자산 성장률(T10Y, S&P 500) | F8: 150000000 | G8: 300000000 | H8: 0.38 | I8: 20440000
A9: US Withholding Rate | B9: 0.15 | C9: % | D9: 미국 과세대상 배당 원천세율, 한미조세협약 | F9: 300000000 | G9: 500000000 | H9: 0.4 | I9: 25440000
A10: Korea Target Dividend WHT | B10: 0.14 | C10: % | D10: 한국 배당소득세 목표 원천세율 | F10: 500000000 | G10: 1000000000 | H10: 0.42 | I10: 35440000
A11: Local Tax Rate | B11: 0.1 | C11: % of income tax | D11: 지방소득세율 | F11: 1000000000 | H11: 0.45 | I11: 72340000
A12: Health + LTC Rate | B12: =8.134% -> 0.08134 | C12: % | D12: 건보+장기요양
A13: Employee Extra-income Threshold | B13: 20000000 | C13: KRW | D13: 직장가입자 보수외소득 기준
A14: Subscriber Type | B14: Local | C14: Employee/Local | D14: 직장가입자 또는 지역가입자

Sheet Calculation
A1: Single Case Calculation / 단일 사례 계산
A3: Item | B3: Value | C3: Unit | D3: Explanation | E3: Formula
A4: Starting Asset A0 | B4: =Inputs!B4 -> 823100000 | C4: KRW | D4: 시작자산 | E4: =Inputs!B4
A5: Existing Taxable Income | B5: =Inputs!B5 -> 9000000 | C5: KRW | D5: 기존 과세표준 | E5: =Inputs!B5
A6: Distribution Rate y | B6: =Inputs!B6 -> 1 | C6: % | D6: 분배율 | E6: =Inputs!B6
A7: ROC Ratio r | B7: =Inputs!B7 -> 0.89 | C7: % | D7: ROC 비중 | E7: =Inputs!B7
A8: Growth Rate g | B8: =Inputs!B8 -> 0 | C8: % | D8: 자산 성장률 | E8: =Inputs!B8
A9: Distribution D | B9: =B4*B6 -> 823100000 | C9: KRW | D9: 분배금 | E9: =A0*y
A10: Taxable Non-ROC Portion | B10: =B9*(1-B7) -> 90541000 | C10: KRW | D10: 미국 과세대상 | E10: =D*(1-r)
A11: ROC Amount | B11: =B9*B7 -> 732559000 | C11: KRW | D11: 원금반환 | E11: =D*r
A12: US Tax Rate on Whole Distribution | B12: =Inputs!B9*(1-B7) -> 0.0165 | C12: % | D12: 전체 분배금 대비 미국세율 | E12: =15%*(1-r)
A13: US Tax Amount | B13: =B9*B12 -> 13581150 | C13: KRW | D13: 미국세 | E13: =D*US rate
A14: KR Differential WHT Rate | B14: =MAX(0,Inputs!B10-B12) -> 0.1235 | C14: % | D14: 한국 14% 목표 원천세와 미국세율 차액 | E14: =MAX(0,14%-US rate)
A15: KR Differential WHT Amount | B15: =B9*B14 -> 101652850 | C15: KRW | D15: 한국 기납 배당소득세 차액 | E15: =D*diff rate
A16: Total Tax Base | B16: =B5+B9 -> 832100000 | C16: KRW | D16: 기존소득 + 분배금 | E16: =existing income + D
A17: Income Tax Before Distribution | B17: =MAX(0,IF(B5<=14000000,B5*0.06,IF(B5<=50000000,B5*0.14-1260000,IF(B5<=88000000,B5*0.24-6260000,IF(B5<=150000000,B5*0.35-15940000,IF(B5<=300000000,B5*0.38-20440000,IF(B5<=500000000,B5*0.4-25440000,IF(B5<=1000000000,B5*0.42-35440000,B5*0.45-72340000)))))))) -> 540000 | C17: KRW | D17: 기존소득 산출세액 | E17: 'Korean bracket formula
A18: Income Tax After Distribution | B18: =MAX(0,IF(B16<=14000000,B16*0.06,IF(B16<=50000000,B16*0.14-1260000,IF(B16<=88000000,B16*0.24-6260000,IF(B16<=150000000,B16*0.35-15940000,IF(B16<=300000000,B16*0.38-20440000,IF(B16<=500000000,B16*0.4-25440000,IF(B16<=1000000000,B16*0.42-35440000,B16*0.45-72340000)))))))) -> 314042000 | C18: KRW | D18: 합산 후 산출세액 | E18: 'Korean bracket formula
A19: Incremental Income Tax | B19: =B18-B17 -> 313502000 | C19: KRW | D19: 분배금으로 증가한 소득세 | E19: =after-before
A20: Incremental Local Tax | B20: =B19*Inputs!B11 -> 31350200 | C20: KRW | D20: 지방소득세 | E20: =income tax increment*10%
A21: Health + LTC Base | B21: =IF(Inputs!B14="Employee",MAX(0,B9-Inputs!B13),B9) -> 823100000 | C21: KRW | D21: 직장: 2천만원 초과분, 지역: 전액 | E21: =IF(Employee,MAX(0,D-threshold),D)
A22: Health + LTC Amount | B22: =B21*Inputs!B12 -> 66950954 | C22: KRW | D22: 건보+장기요양 | E22: =base*8.134%
A23: KR Total Additional Burden | B23: =B19+B20+B22 -> 411803154 | C23: KRW | D23: 종소세 증가분 + 지방세 + 건보 | E23: =income tax+local+health
A24: KR Net Cash Due after KR WHT | B24: =MAX(0,B23-B15) -> 310150304 | C24: KRW | D24: 한국 기납 차액원천세 차감 후 추가 현금부담 | E24: =MAX(0,total burden-KR WHT)
A25: KR/US Burden Multiple | B25: =IF(B13=0,"Undefined",B23/B13) -> 30.32167 | C25: x | D25: 한국 총부담 / 미국세 | E25: =KR total/US tax
A26: 1Y Asset Reinvested - US | B26: =B4*(1+B8)-B13 -> 809518850 | C26: KRW | D26: 분배금 재투자, 미국세 차감 | E26: =A0*(1+g)-US tax
A27: 1Y Asset Reinvested - KR | B27: =B4*(1+B8)-B23 -> 411296846 | C27: KRW | D27: 분배금 재투자, 한국 총부담 차감 | E27: =A0*(1+g)-KR burden
A28: 1Y Asset Consumed - US | B28: =B4*(1+B8)-B9-B13 -> -13581150 | C28: KRW | D28: 분배금 소비, 미국 | E28: =A0*(1+g)-D-US tax
A29: 1Y Asset Consumed - KR | B29: =B4*(1+B8)-B9-B23 -> -411803154 | C29: KRW | D29: 분배금 소비, 한국, 자기자본 피해금액 | E29: =A0*(1+g)-D-KR burden
A30: 1Y Asset Consumed DIFF. - KR-US | B30: =B29-B28 -> -398222004 | C30: KRW | D30: 한국거주자 자기자본과세 피해금액 | E30: =A0*(1+g)-D-KR burden -A0*(1+g)-D-US tax

Sheet Scenario_Table
A1: Scenario Table / 분배율·ROC 비중별 계산표
A3: Distribution Rate y | B3: ROC Ratio r | C3: Distribution D | D3: US Tax Rate | E3: US Tax Amount | F3: KR Diff WHT Rate | G3: KR Diff WHT Amount | H3: KR Total Burden | I3: KR/US Multiple | J3: 1Y Reinvested US Asset | K3: 1Y Reinvested KR Asset
A4: 0.5 | B4: 0 | C4: =Inputs!$B$4*A4 -> 411550000 | D4: =Inputs!$B$9*(1-B4) -> 0.15 | E4: =C4*D4 -> 61732500 | F4: =MAX(0,Inputs!$B$10-D4) -> 0 | G4: =C4*F4 -> 0 | H4: =(MAX(0,IF((Inputs!$B$5+C4)<=14000000,(Inputs!$B$5+C4)*0.06,IF((Inputs!$B$5+C4)<=50000000,(Inputs!$B$5+C4)*0.14-1260000,IF((Inputs!$B$5+C4)<=88000000,(Inputs!$B$5+C4)*0.24-6260000,IF((Inputs!$B$5+C4)<=150000000,(Inputs!$B$5+C4)*0.35-15940000,IF((Inputs!$B$5+C4)<=300000000,(Inputs!$B$5+C4)*0.38-20440000,IF((Inputs!$B$5+C4)<=500000000,(Inputs!$B$5+C4)*0.4-25440000,IF((Inputs!$B$5+C4)<=1000000000,(Inputs!$B$5+C4)*0.42-35440000,(Inputs!$B$5+C4)*0.45-72340000)))))))))-(MAX(0,IF(Inputs!$B$5<=14000000,Inputs!$B$5*0.06,IF(Inputs!$B$5<=50000000,Inputs!$B$5*0.14-1260000,IF(Inputs!$B$5<=88000000,Inputs!$B$5*0.24-6260000,IF(Inputs!$B$5<=150000000,Inputs!$B$5*0.35-15940000,IF(Inputs!$B$5<=300000000,Inputs!$B$5*0.38-20440000,IF(Inputs!$B$5<=500000000,Inputs!$B$5*0.4-25440000,IF(Inputs!$B$5<=1000000000,Inputs!$B$5*0.42-35440000,Inputs!$B$5*0.45-72340000)))))))))+(((MAX(0,IF((Inputs!$B$5+C4)<=14000000,(Inputs!$B$5+C4)*0.06,IF((Inputs!$B$5+C4)<=50000000,(Inputs!$B$5+C4)*0.14-1260000,IF((Inputs!$B$5+C4)<=88000000,(Inputs!$B$5+C4)*0.24-6260000,IF((Inputs!$B$5+C4)<=150000000,(Inputs!$B$5+C4)*0.35-15940000,IF((Inputs!$B$5+C4)<=300000000,(Inputs!$B$5+C4)*0.38-20440000,IF((Inputs!$B$5+C4)<=500000000,(Inputs!$B$5+C4)*0.4-25440000,IF((Inputs!$B$5+C4)<=1000000000,(Inputs!$B$5+C4)*0.42-35440000,(Inputs!$B$5+C4)*0.45-72340000)))))))))-(MAX(0,IF(Inputs!$B$5<=14000000,Inputs!$B$5*0.06,IF(Inputs!$B$5<=50000000,Inputs!$B$5*0.14-1260000,IF(Inputs!$B$5<=88000000,Inputs!$B$5*0.24-6260000,IF(Inputs!$B$5<=150000000,Inputs!$B$5*0.35-15940000,IF(Inputs!$B$5<=300000000,Inputs!$B$5*0.38-20440000,IF(Inputs!$B$5<=500000000,Inputs!$B$5*0.4-25440000,IF(Inputs!$B$5<=1000000000,Inputs!$B$5*0.42-35440000,Inputs!$B$5*0.45-72340000))))))))))*Inputs!$B$11)+((IF(Inputs!$B$14="Employee",MAX(0,C4-Inputs!$B$13),C4))*Inputs!$B$12) -> 189939477 | I4: =IF(E4=0,"Undefined",H4/E4) -> 3.0768149 | J4: =Inputs!$B$4*(1+Inputs!$B$8)-E4 -> 761367500 | K4: =Inputs!$B$4*(1+Inputs!$B$8)-H4 -> 633160523
A5: 0.5 | B5: 0.3 | C5: =Inputs!$B$4*A5 -> 411550000 | D5: =Inputs!$B$9*(1-B5) -> 0.105 | E5: =C5*D5 -> 43212750 | F5: =MAX(0,Inputs!$B$10-D5) -> 0.035 | G5: =C5*F5 -> 14404250 | H5: =(MAX(0,IF((Inputs!$B$5+C5)<=14000000,(Inputs!$B$5+C5)*0.06,IF((Inputs!$B$5+C5)<=50000000,(Inputs!$B$5+C5)*0.14-1260000,IF((Inputs!$B$5+C5)<=88000000,(Inputs!$B$5+C5)*0.24-6260000,IF((Inputs!$B$5+C5)<=150000000,(Inputs!$B$5+C5)*0.35-15940000,IF((Inputs!$B$5+C5)<=300000000,(Inputs!$B$5+C5)*0.38-20440000,IF((Inputs!$B$5+C5)<=500000000,(Inputs!$B$5+C5)*0.4-25440000,IF((Inputs!$B$5+C5)<=1000000000,(Inputs!$B$5+C5)*0.42-35440000,(Inputs!$B$5+C5)*0.45-72340000)))))))))-(MAX(0,IF(Inputs!$B$5<=14000000,Inputs!$B$5*0.06,IF(Inputs!$B$5<=50000000,Inputs!$B$5*0.14-1260000,IF(Inputs!$B$5<=88000000,Inputs!$B$5*0.24-6260000,IF(Inputs!$B$5<=150000000,Inputs!$B$5*0.35-15940000,IF(Inputs!$B$5<=300000000,Inputs!$B$5*0.38-20440000,IF(Inputs!$B$5<=500000000,Inputs!$B$5*0.4-25440000,IF(Inputs!$B$5<=1000000000,Inputs!$B$5*0.42-35440000,Inputs!$B$5*0.45-72340000)))))))))+(((MAX(0,IF((Inputs!$B$5+C5)<=14000000,(Inputs!$B$5+C5)*0.06,IF((Inputs!$B$5+C5)<=50000000,(Inputs!$B$5+C5)*0.14-1260000,IF((Inputs!$B$5+C5)<=88000000,(Inputs!$B$5+C5)*0.24-6260000,IF((Inputs!$B$5+C5)<=150000000,(Inputs!$B$5+C5)*0.35-15940000,IF((Inputs!$B$5+C5)<=300000000,(Inputs!$B$5+C5)*0.38-20440000,IF((Inputs!$B$5+C5)<=500000000,(Inputs!$B$5+C5)*0.4-25440000,IF((Inputs!$B$5+C5)<=1000000000,(Inputs!$B$5+C5)*0.42-35440000,(Inputs!$B$5+C5)*0.45-72340000)))))))))-(MAX(0,IF(Inputs!$B$5<=14000000,Inputs!$B$5*0.06,IF(Inputs!$B$5<=50000000,Inputs!$B$5*0.14-1260000,IF(Inputs!$B$5<=88000000,Inputs!$B$5*0.24-6260000,IF(Inputs!$B$5<=150000000,Inputs!$B$5*0.35-15940000,IF(Inputs!$B$5<=300000000,Inputs!$B$5*0.38-20440000,IF(Inputs!$B$5<=500000000,Inputs!$B$5*0.4-25440000,IF(Inputs!$B$5<=1000000000,Inputs!$B$5*0.42-35440000,Inputs!$B$5*0.45-72340000))))))))))*Inputs!$B$11)+((IF(Inputs!$B$14="Employee",MAX(0,C5-Inputs!$B$13),C5))*Inputs!$B$12) -> 189939477 | I5: =IF(E5=0,"Undefined",H5/E5) -> 4.3954499 | J5: =Inputs!$B$4*(1+Inputs!$B$8)-E5 -> 779887250 | K5: =Inputs!$B$4*(1+Inputs!$B$8)-H5 -> 633160523
A6: 0.5 | B6: 0.6 | C6: =Inputs!$B$4*A6 -> 411550000 | D6: =Inputs!$B$9*(1-B6) -> 0.06 | E6: =C6*D6 -> 24693000 | F6: =MAX(0,Inputs!$B$10-D6) -> 0.08 | G6: =C6*F6 -> 32924000 | H6: =(MAX(0,IF((Inputs!$B$5+C6)<=14000000,(Inputs!$B$5+C6)*0.06,IF((Inputs!$B$5+C6)<=50000000,(Inputs!$B$5+C6)*0.14-1260000,IF((Inputs!$B$5+C6)<=88000000,(Inputs!$B$5+C6)*0.24-6260000,IF((Inputs!$B$5+C6)<=150000000,(Inputs!$B$5+C6)*0.35-15940000,IF((Inputs!$B$5+C6)<=300000000,(Inputs!$B$5+C6)*0.38-20440000,IF((Inputs!$B$5+C6)<=500000000,(Inputs!$B$5+C6)*0.4-25440000,IF((Inputs!$B$5+C6)<=1000000000,(Inputs!$B$5+C6)*0.42-35440000,(Inputs!$B$5+C6)*0.45-72340000)))))))))-(MAX(0,IF(Inputs!$B$5<=14000000,Inputs!$B$5*0.06,IF(Inputs!$B$5<=50000000,Inputs!$B$5*0.14-1260000,IF(Inputs!$B$5<=88000000,Inputs!$B$5*0.24-6260000,IF(Inputs!$B$5<=150000000,Inputs!$B$5*0.35-15940000,IF(Inputs!$B$5<=300000000,Inputs!$B$5*0.38-20440000,IF(Inputs!$B$5<=500000000,Inputs!$B$5*0.4-25440000,IF(Inputs!$B$5<=1000000000,Inputs!$B$5*0.42-35440000,Inputs!$B$5*0.45-72340000)))))))))+(((MAX(0,IF((Inputs!$B$5+C6)<=14000000,(Inputs!$B$5+C6)*0.06,IF((Inputs!$B$5+C6)<=50000000,(Inputs!$B$5+C6)*0.14-1260000,IF((Inputs!$B$5+C6)<=88000000,(Inputs!$B$5+C6)*0.24-6260000,IF((Inputs!$B$5+C6)<=150000000,(Inputs!$B$5+C6)*0.35-15940000,IF((Inputs!$B$5+C6)<=300000000,(Inputs!$B$5+C6)*0.38-20440000,IF((Inputs!$B$5+C6)<=500000000,(Inputs!$B$5+C6)*0.4-25440000,IF((Inputs!$B$5+C6)<=1000000000,(Inputs!$B$5+C6)*0.42-35440000,(Inputs!$B$5+C6)*0.45-72340000)))))))))-(MAX(0,IF(Inputs!$B$5<=14000000,Inputs!$B$5*0.06,IF(Inputs!$B$5<=50000000,Inputs!$B$5*0.14-1260000,IF(Inputs!$B$5<=88000000,Inputs!$B$5*0.24-6260000,IF(Inputs!$B$5<=150000000,Inputs!$B$5*0.35-15940000,IF(Inputs!$B$5<=300000000,Inputs!$B$5*0.38-20440000,IF(Inputs!$B$5<=500000000,Inputs!$B$5*0.4-25440000,IF(Inputs!$B$5<=1000000000,Inputs!$B$5*0.42-35440000,Inputs!$B$5*0.45-72340000))))))))))*Inputs!$B$11)+((IF(Inputs!$B$14="Employee",MAX(0,C6-Inputs!$B$13),C6))*Inputs!$B$12) -> 189939477 | I6: =IF(E6=0,"Undefined",H6/E6) -> 7.6920373 | J6: =Inputs!$B$4*(1+Inputs!$B$8)-E6 -> 798407000 | K6: =Inputs!$B$4*(1+Inputs!$B$8)-H6 -> 633160523
A7: 0.5 | B7: 0.9 | C7: =Inputs!$B$4*A7 -> 411550000 | D7: =Inputs!$B$9*(1-B7) -> 0.015 | E7: =C7*D7 -> 6173250 | F7: =MAX(0,Inputs!$B$10-D7) -> 0.125 | G7: =C7*F7 -> 51443750 | H7: =(MAX(0,IF((Inputs!$B$5+C7)<=14000000,(Inputs!$B$5+C7)*0.06,IF((Inputs!$B$5+C7)<=50000000,(Inputs!$B$5+C7)*0.14-1260000,IF((Inputs!$B$5+C7)<=88000000,(Inputs!$B$5+C7)*0.24-6260000,IF((Inputs!$B$5+C7)<=150000000,(Inputs!$B$5+C7)*0.35-15940000,IF((Inputs!$B$5+C7)<=300000000,(Inputs!$B$5+C7)*0.38-20440000,IF((Inputs!$B$5+C7)<=500000000,(Inputs!$B$5+C7)*0.4-25440000,IF((Inputs!$B$5+C7)<=1000000000,(Inputs!$B$5+C7)*0.42-35440000,(Inputs!$B$5+C7)*0.45-72340000)))))))))-(MAX(0,IF(Inputs!$B$5<=14000000,Inputs!$B$5*0.06,IF(Inputs!$B$5<=50000000,Inputs!$B$5*0.14-1260000,IF(Inputs!$B$5<=88000000,Inputs!$B$5*0.24-6260000,IF(Inputs!$B$5<=150000000,Inputs!$B$5*0.35-15940000,IF(Inputs!$B$5<=300000000,Inputs!$B$5*0.38-20440000,IF(Inputs!$B$5<=500000000,Inputs!$B$5*0.4-25440000,IF(Inputs!$B$5<=1000000000,Inputs!$B$5*0.42-35440000,Inputs!$B$5*0.45-72340000)))))))))+(((MAX(0,IF((Inputs!$B$5+C7)<=14000000,(Inputs!$B$5+C7)*0.06,IF((Inputs!$B$5+C7)<=50000000,(Inputs!$B$5+C7)*0.14-1260000,IF((Inputs!$B$5+C7)<=88000000,(Inputs!$B$5+C7)*0.24-6260000,IF((Inputs!$B$5+C7)<=150000000,(Inputs!$B$5+C7)*0.35-15940000,IF((Inputs!$B$5+C7)<=300000000,(Inputs!$B$5+C7)*0.38-20440000,IF((Inputs!$B$5+C7)<=500000000,(Inputs!$B$5+C7)*0.4-25440000,IF((Inputs!$B$5+C7)<=1000000000,(Inputs!$B$5+C7)*0.42-35440000,(Inputs!$B$5+C7)*0.45-72340000)))))))))-(MAX(0,IF(Inputs!$B$5<=14000000,Inputs!$B$5*0.06,IF(Inputs!$B$5<=50000000,Inputs!$B$5*0.14-1260000,IF(Inputs!$B$5<=88000000,Inputs!$B$5*0.24-6260000,IF(Inputs!$B$5<=150000000,Inputs!$B$5*0.35-15940000,IF(Inputs!$B$5<=300000000,Inputs!$B$5*0.38-20440000,IF(Inputs!$B$5<=500000000,Inputs!$B$5*0.4-25440000,IF(Inputs!$B$5<=1000000000,Inputs!$B$5*0.42-35440000,Inputs!$B$5*0.45-72340000))))))))))*Inputs!$B$11)+((IF(Inputs!$B$14="Employee",MAX(0,C7-Inputs!$B$13),C7))*Inputs!$B$12) -> 189939477 | I7: =IF(E7=0,"Undefined",H7/E7) -> 30.768149 | J7: =Inputs!$B$4*(1+Inputs!$B$8)-E7 -> 816926750 | K7: =Inputs!$B$4*(1+Inputs!$B$8)-H7 -> 633160523
A8: 0.5 | B8: 0.99 | C8: =Inputs!$B$4*A8 -> 411550000 | D8: =Inputs!$B$9*(1-B8) -> 0.0015 | E8: =C8*D8 -> 617325 | F8: =MAX(0,Inputs!$B$10-D8) -> 0.1385 | G8: =C8*F8 -> 56999675 | H8: =(MAX(0,IF((Inputs!$B$5+C8)<=14000000,(Inputs!$B$5+C8)*0.06,IF((Inputs!$B$5+C8)<=50000000,(Inputs!$B$5+C8)*0.14-1260000,IF((Inputs!$B$5+C8)<=88000000,(Inputs!$B$5+C8)*0.24-6260000,IF((Inputs!$B$5+C8)<=150000000,(Inputs!$B$5+C8)*0.35-15940000,IF((Inputs!$B$5+C8)<=300000000,(Inputs!$B$5+C8)*0.38-20440000,IF((Inputs!$B$5+C8)<=500000000,(Inputs!$B$5+C8)*0.4-25440000,IF((Inputs!$B$5+C8)<=1000000000,(Inputs!$B$5+C8)*0.42-35440000,(Inputs!$B$5+C8)*0.45-72340000)))))))))-(MAX(0,IF(Inputs!$B$5<=14000000,Inputs!$B$5*0.06,IF(Inputs!$B$5<=50000000,Inputs!$B$5*0.14-1260000,IF(Inputs!$B$5<=88000000,Inputs!$B$5*0.24-6260000,IF(Inputs!$B$5<=150000000,Inputs!$B$5*0.35-15940000,IF(Inputs!$B$5<=300000000,Inputs!$B$5*0.38-20440000,IF(Inputs!$B$5<=500000000,Inputs!$B$5*0.4-25440000,IF(Inputs!$B$5<=1000000000,Inputs!$B$5*0.42-35440000,Inputs!$B$5*0.45-72340000)))))))))+(((MAX(0,IF((Inputs!$B$5+C8)<=14000000,(Inputs!$B$5+C8)*0.06,IF((Inputs!$B$5+C8)<=50000000,(Inputs!$B$5+C8)*0.14-1260000,IF((Inputs!$B$5+C8)<=88000000,(Inputs!$B$5+C8)*0.24-6260000,IF((Inputs!$B$5+C8)<=150000000,(Inputs!$B$5+C8)*0.35-15940000,IF((Inputs!$B$5+C8)<=300000000,(Inputs!$B$5+C8)*0.38-20440000,IF((Inputs!$B$5+C8)<=500000000,(Inputs!$B$5+C8)*0.4-25440000,IF((Inputs!$B$5+C8)<=1000000000,(Inputs!$B$5+C8)*0.42-35440000,(Inputs!$B$5+C8)*0.45-72340000)))))))))-(MAX(0,IF(Inputs!$B$5<=14000000,Inputs!$B$5*0.06,IF(Inputs!$B$5<=50000000,Inputs!$B$5*0.14-1260000,IF(Inputs!$B$5<=88000000,Inputs!$B$5*0.24-6260000,IF(Inputs!$B$5<=150000000,Inputs!$B$5*0.35-15940000,IF(Inputs!$B$5<=300000000,Inputs!$B$5*0.38-20440000,IF(Inputs!$B$5<=500000000,Inputs!$B$5*0.4-25440000,IF(Inputs!$B$5<=1000000000,Inputs!$B$5*0.42-35440000,Inputs!$B$5*0.45-72340000))))))))))*Inputs!$B$11)+((IF(Inputs!$B$14="Employee",MAX(0,C8-Inputs!$B$13),C8))*Inputs!$B$12) -> 189939477 | I8: =IF(E8=0,"Undefined",H8/E8) -> 307.68149 | J8: =Inputs!$B$4*(1+Inputs!$B$8)-E8 -> 822482675 | K8: =Inputs!$B$4*(1+Inputs!$B$8)-H8 -> 633160523
A9: 0.5 | B9: 1 | C9: =Inputs!$B$4*A9 -> 411550000 | D9: =Inputs!$B$9*(1-B9) -> 0 | E9: =C9*D9 -> 0 | F9: =MAX(0,Inputs!$B$10-D9) -> 0.14 | G9: =C9*F9 -> 57617000 | H9: =(MAX(0,IF((Inputs!$B$5+C9)<=14000000,(Inputs!$B$5+C9)*0.06,IF((Inputs!$B$5+C9)<=50000000,(Inputs!$B$5+C9)*0.14-1260000,IF((Inputs!$B$5+C9)<=88000000,(Inputs!$B$5+C9)*0.24-6260000,IF((Inputs!$B$5+C9)<=150000000,(Inputs!$B$5+C9)*0.35-15940000,IF((Inputs!$B$5+C9)<=300000000,(Inputs!$B$5+C9)*0.38-20440000,IF((Inputs!$B$5+C9)<=500000000,(Inputs!$B$5+C9)*0.4-25440000,IF((Inputs!$B$5+C9)<=1000000000,(Inputs!$B$5+C9)*0.42-35440000,(Inputs!$B$5+C9)*0.45-72340000)))))))))-(MAX(0,IF(Inputs!$B$5<=14000000,Inputs!$B$5*0.06,IF(Inputs!$B$5<=50000000,Inputs!$B$5*0.14-1260000,IF(Inputs!$B$5<=88000000,Inputs!$B$5*0.24-6260000,IF(Inputs!$B$5<=150000000,Inputs!$B$5*0.35-15940000,IF(Inputs!$B$5<=300000000,Inputs!$B$5*0.38-20440000,IF(Inputs!$B$5<=500000000,Inputs!$B$5*0.4-25440000,IF(Inputs!$B$5<=1000000000,Inputs!$B$5*0.42-35440000,Inputs!$B$5*0.45-72340000)))))))))+(((MAX(0,IF((Inputs!$B$5+C9)<=14000000,(Inputs!$B$5+C9)*0.06,IF((Inputs!$B$5+C9)<=50000000,(Inputs!$B$5+C9)*0.14-1260000,IF((Inputs!$B$5+C9)<=88000000,(Inputs!$B$5+C9)*0.24-6260000,IF((Inputs!$B$5+C9)<=150000000,(Inputs!$B$5+C9)*0.35-15940000,IF((Inputs!$B$5+C9)<=300000000,(Inputs!$B$5+C9)*0.38-20440000,IF((Inputs!$B$5+C9)<=500000000,(Inputs!$B$5+C9)*0.4-25440000,IF((Inputs!$B$5+C9)<=1000000000,(Inputs!$B$5+C9)*0.42-35440000,(Inputs!$B$5+C9)*0.45-72340000)))))))))-(MAX(0,IF(Inputs!$B$5<=14000000,Inputs!$B$5*0.06,IF(Inputs!$B$5<=50000000,Inputs!$B$5*0.14-1260000,IF(Inputs!$B$5<=88000000,Inputs!$B$5*0.24-6260000,IF(Inputs!$B$5<=150000000,Inputs!$B$5*0.35-15940000,IF(Inputs!$B$5<=300000000,Inputs!$B$5*0.38-20440000,IF(Inputs!$B$5<=500000000,Inputs!$B$5*0.4-25440000,IF(Inputs!$B$5<=1000000000,Inputs!$B$5*0.42-35440000,Inputs!$B$5*0.45-72340000))))))))))*Inputs!$B$11)+((IF(Inputs!$B$14="Employee",MAX(0,C9-Inputs!$B$13),C9))*Inputs!$B$12) -> 189939477 | I9: =IF(E9=0,"Undefined",H9/E9) -> Undefined | J9: =Inputs!$B$4*(1+Inputs!$B$8)-E9 -> 823100000 | K9: =Inputs!$B$4*(1+Inputs!$B$8)-H9 -> 633160523
A10: 0.6 | B10: 0 | C10: =Inputs!$B$4*A10 -> 493860000 | D10: =Inputs!$B$9*(1-B10) -> 0.15 | E10: =C10*D10 -> 74079000 | F10: =MAX(0,Inputs!$B$10-D10) -> 0 | G10: =C10*F10 -> 0 | H10: =(MAX(0,IF((Inputs!$B$5+C10)<=14000000,(Inputs!$B$5+C10)*0.06,IF((Inputs!$B$5+C10)<=50000000,(Inputs!$B$5+C10)*0.14-1260000,IF((Inputs!$B$5+C10)<=88000000,(Inputs!$B$5+C10)*0.24-6260000,IF((Inputs!$B$5+C10)<=150000000,(Inputs!$B$5+C10)*0.35-15940000,IF((Inputs!$B$5+C10)<=300000000,(Inputs!$B$5+C10)*0.38-20440000,IF((Inputs!$B$5+C10)<=500000000,(Inputs!$B$5+C10)*0.4-25440000,IF((Inputs!$B$5+C10)<=1000000000,(Inputs!$B$5+C10)*0.42-35440000,(Inputs!$B$5+C10)*0.45-72340000)))))))))-(MAX(0,IF(Inputs!$B$5<=14000000,Inputs!$B$5*0.06,IF(Inputs!$B$5<=50000000,Inputs!$B$5*0.14-1260000,IF(Inputs!$B$5<=88000000,Inputs!$B$5*0.24-6260000,IF(Inputs!$B$5<=150000000,Inputs!$B$5*0.35-15940000,IF(Inputs!$B$5<=300000000,Inputs!$B$5*0.38-20440000,IF(Inputs!$B$5<=500000000,Inputs!$B$5*0.4-25440000,IF(Inputs!$B$5<=1000000000,Inputs!$B$5*0.42-35440000,Inputs!$B$5*0.45-72340000)))))))))+(((MAX(0,IF((Inputs!$B$5+C10)<=14000000,(Inputs!$B$5+C10)*0.06,IF((Inputs!$B$5+C10)<=50000000,(Inputs!$B$5+C10)*0.14-1260000,IF((Inputs!$B$5+C10)<=88000000,(Inputs!$B$5+C10)*0.24-6260000,IF((Inputs!$B$5+C10)<=150000000,(Inputs!$B$5+C10)*0.35-15940000,IF((Inputs!$B$5+C10)<=300000000,(Inputs!$B$5+C10)*0.38-20440000,IF((Inputs!$B$5+C10)<=500000000,(Inputs!$B$5+C10)*0.4-25440000,IF((Inputs!$B$5+C10)<=1000000000,(Inputs!$B$5+C10)*0.42-35440000,(Inputs!$B$5+C10)*0.45-72340000)))))))))-(MAX(0,IF(Inputs!$B$5<=14000000,Inputs!$B$5*0.06,IF(Inputs!$B$5<=50000000,Inputs!$B$5*0.14-1260000,IF(Inputs!$B$5<=88000000,Inputs!$B$5*0.24-6260000,IF(Inputs!$B$5<=150000000,Inputs!$B$5*0.35-15940000,IF(Inputs!$B$5<=300000000,Inputs!$B$5*0.38-20440000,IF(Inputs!$B$5<=500000000,Inputs!$B$5*0.4-25440000,IF(Inputs!$B$5<=1000000000,Inputs!$B$5*0.42-35440000,Inputs!$B$5*0.45-72340000))))))))))*Inputs!$B$11)+((IF(Inputs!$B$14="Employee",MAX(0,C10-Inputs!$B$13),C10))*Inputs!$B$12) -> 2.3291389e+08 | I10: =IF(E10=0,"Undefined",H10/E10) -> 3.1441285 | J10: =Inputs!$B$4*(1+Inputs!$B$8)-E10 -> 749021000 | K10: =Inputs!$B$4*(1+Inputs!$B$8)-H10 -> 5.9018611e+08
A11: 0.6 | B11: 0.3 | C11: =Inputs!$B$4*A11 -> 493860000 | D11: =Inputs!$B$9*(1-B11) -> 0.105 | E11: =C11*D11 -> 51855300 | F11: =MAX(0,Inputs!$B$10-D11) -> 0.035 | G11: =C11*F11 -> 17285100 | H11: =(MAX(0,IF((Inputs!$B$5+C11)<=14000000,(Inputs!$B$5+C11)*0.06,IF((Inputs!$B$5+C11)<=50000000,(Inputs!$B$5+C11)*0.14-1260000,IF((Inputs!$B$5+C11)<=88000000,(Inputs!$B$5+C11)*0.24-6260000,IF((Inputs!$B$5+C11)<=150000000,(Inputs!$B$5+C11)*0.35-15940000,IF((Inputs!$B$5+C11)<=300000000,(Inputs!$B$5+C11)*0.38-20440000,IF((Inputs!$B$5+C11)<=500000000,(Inputs!$B$5+C11)*0.4-25440000,IF((Inputs!$B$5+C11)<=1000000000,(Inputs!$B$5+C11)*0.42-35440000,(Inputs!$B$5+C11)*0.45-72340000)))))))))-(MAX(0,IF(Inputs!$B$5<=14000000,Inputs!$B$5*0.06,IF(Inputs!$B$5<=50000000,Inputs!$B$5*0.14-1260000,IF(Inputs!$B$5<=88000000,Inputs!$B$5*0.24-6260000,IF(Inputs!$B$5<=150000000,Inputs!$B$5*0.35-15940000,IF(Inputs!$B$5<=300000000,Inputs!$B$5*0.38-20440000,IF(Inputs!$B$5<=500000000,Inputs!$B$5*0.4-25440000,IF(Inputs!$B$5<=1000000000,Inputs!$B$5*0.42-35440000,Inputs!$B$5*0.45-72340000)))))))))+(((MAX(0,IF((Inputs!$B$5+C11)<=14000000,(Inputs!$B$5+C11)*0.06,IF((Inputs!$B$5+C11)<=50000000,(Inputs!$B$5+C11)*0.14-1260000,IF((Inputs!$B$5+C11)<=88000000,(Inputs!$B$5+C11)*0.24-6260000,IF((Inputs!$B$5+C11)<=150000000,(Inputs!$B$5+C11)*0.35-15940000,IF((Inputs!$B$5+C11)<=300000000,(Inputs!$B$5+C11)*0.38-20440000,IF((Inputs!$B$5+C11)<=500000000,(Inputs!$B$5+C11)*0.4-25440000,IF((Inputs!$B$5+C11)<=1000000000,(Inputs!$B$5+C11)*0.42-35440000,(Inputs!$B$5+C11)*0.45-72340000)))))))))-(MAX(0,IF(Inputs!$B$5<=14000000,Inputs!$B$5*0.06,IF(Inputs!$B$5<=50000000,Inputs!$B$5*0.14-1260000,IF(Inputs!$B$5<=88000000,Inputs!$B$5*0.24-6260000,IF(Inputs!$B$5<=150000000,Inputs!$B$5*0.35-15940000,IF(Inputs!$B$5<=300000000,Inputs!$B$5*0.38-20440000,IF(Inputs!$B$5<=500000000,Inputs!$B$5*0.4-25440000,IF(Inputs!$B$5<=1000000000,Inputs!$B$5*0.42-35440000,Inputs!$B$5*0.45-72340000))))))))))*Inputs!$B$11)+((IF(Inputs!$B$14="Employee",MAX(0,C11-Inputs!$B$13),C11))*Inputs!$B$12) -> 2.3291389e+08 | I11: =IF(E11=0,"Undefined",H11/E11) -> 4.4916121 | J11: =Inputs!$B$4*(1+Inputs!$B$8)-E11 -> 771244700 | K11: =Inputs!$B$4*(1+Inputs!$B$8)-H11 -> 5.9018611e+08
A12: 0.6 | B12: 0.6 | C12: =Inputs!$B$4*A12 -> 493860000 | D12: =Inputs!$B$9*(1-B12) -> 0.06 | E12: =C12*D12 -> 29631600 | F12: =MAX(0,Inputs!$B$10-D12) -> 0.08 | G12: =C12*F12 -> 39508800 | H12: =(MAX(0,IF((Inputs!$B$5+C12)<=14000000,(Inputs!$B$5+C12)*0.06,IF((Inputs!$B$5+C12)<=50000000,(Inputs!$B$5+C12)*0.14-1260000,IF((Inputs!$B$5+C12)<=88000000,(Inputs!$B$5+C12)*0.24-6260000,IF((Inputs!$B$5+C12)<=150000000,(Inputs!$B$5+C12)*0.35-15940000,IF((Inputs!$B$5+C12)<=300000000,(Inputs!$B$5+C12)*0.38-20440000,IF((Inputs!$B$5+C12)<=500000000,(Inputs!$B$5+C12)*0.4-25440000,IF((Inputs!$B$5+C12)<=1000000000,(Inputs!$B$5+C12)*0.42-35440000,(Inputs!$B$5+C12)*0.45-72340000)))))))))-(MAX(0,IF(Inputs!$B$5<=14000000,Inputs!$B$5*0.06,IF(Inputs!$B$5<=50000000,Inputs!$B$5*0.14-1260000,IF(Inputs!$B$5<=88000000,Inputs!$B$5*0.24-6260000,IF(Inputs!$B$5<=150000000,Inputs!$B$5*0.35-15940000,IF(Inputs!$B$5<=300000000,Inputs!$B$5*0.38-20440000,IF(Inputs!$B$5<=500000000,Inputs!$B$5*0.4-25440000,IF(Inputs!$B$5<=1000000000,Inputs!$B$5*0.42-35440000,Inputs!$B$5*0.45-72340000)))))))))+(((MAX(0,IF((Inputs!$B$5+C12)<=14000000,(Inputs!$B$5+C12)*0.06,IF((Inputs!$B$5+C12)<=50000000,(Inputs!$B$5+C12)*0.14-1260000,IF((Inputs!$B$5+C12)<=88000000,(Inputs!$B$5+C12)*0.24-6260000,IF((Inputs!$B$5+C12)<=150000000,(Inputs!$B$5+C12)*0.35-15940000,IF((Inputs!$B$5+C12)<=300000000,(Inputs!$B$5+C12)*0.38-20440000,IF((Inputs!$B$5+C12)<=500000000,(Inputs!$B$5+C12)*0.4-25440000,IF((Inputs!$B$5+C12)<=1000000000,(Inputs!$B$5+C12)*0.42-35440000,(Inputs!$B$5+C12)*0.45-72340000)))))))))-(MAX(0,IF(Inputs!$B$5<=14000000,Inputs!$B$5*0.06,IF(Inputs!$B$5<=50000000,Inputs!$B$5*0.14-1260000,IF(Inputs!$B$5<=88000000,Inputs!$B$5*0.24-6260000,IF(Inputs!$B$5<=150000000,Inputs!$B$5*0.35-15940000,IF(Inputs!$B$5<=300000000,Inputs!$B$5*0.38-20440000,IF(Inputs!$B$5<=500000000,Inputs!$B$5*0.4-25440000,IF(Inputs!$B$5<=1000000000,Inputs!$B$5*0.42-35440000,Inputs!$B$5*0.45-72340000))))))))))*Inputs!$B$11)+((IF(Inputs!$B$14="Employee",MAX(0,C12-Inputs!$B$13),C12))*Inputs!$B$12) -> 2.3291389e+08 | I12: =IF(E12=0,"Undefined",H12/E12) -> 7.8603212 | J12: =Inputs!$B$4*(1+Inputs!$B$8)-E12 -> 793468400 | K12: =Inputs!$B$4*(1+Inputs!$B$8)-H12 -> 5.9018611e+08
A13: 0.6 | B13: 0.9 | C13: =Inputs!$B$4*A13 -> 493860000 | D13: =Inputs!$B$9*(1-B13) -> 0.015 | E13: =C13*D13 -> 7407900 | F13: =MAX(0,Inputs!$B$10-D13) -> 0.125 | G13: =C13*F13 -> 61732500 | H13: =(MAX(0,IF((Inputs!$B$5+C13)<=14000000,(Inputs!$B$5+C13)*0.06,IF((Inputs!$B$5+C13)<=50000000,(Inputs!$B$5+C13)*0.14-1260000,IF((Inputs!$B$5+C13)<=88000000,(Inputs!$B$5+C13)*0.24-6260000,IF((Inputs!$B$5+C13)<=150000000,(Inputs!$B$5+C13)*0.35-15940000,IF((Inputs!$B$5+C13)<=300000000,(Inputs!$B$5+C13)*0.38-20440000,IF((Inputs!$B$5+C13)<=500000000,(Inputs!$B$5+C13)*0.4-25440000,IF((Inputs!$B$5+C13)<=1000000000,(Inputs!$B$5+C13)*0.42-35440000,(Inputs!$B$5+C13)*0.45-72340000)))))))))-(MAX(0,IF(Inputs!$B$5<=14000000,Inputs!$B$5*0.06,IF(Inputs!$B$5<=50000000,Inputs!$B$5*0.14-1260000,IF(Inputs!$B$5<=88000000,Inputs!$B$5*0.24-6260000,IF(Inputs!$B$5<=150000000,Inputs!$B$5*0.35-15940000,IF(Inputs!$B$5<=300000000,Inputs!$B$5*0.38-20440000,IF(Inputs!$B$5<=500000000,Inputs!$B$5*0.4-25440000,IF(Inputs!$B$5<=1000000000,Inputs!$B$5*0.42-35440000,Inputs!$B$5*0.45-72340000)))))))))+(((MAX(0,IF((Inputs!$B$5+C13)<=14000000,(Inputs!$B$5+C13)*0.06,IF((Inputs!$B$5+C13)<=50000000,(Inputs!$B$5+C13)*0.14-1260000,IF((Inputs!$B$5+C13)<=88000000,(Inputs!$B$5+C13)*0.24-6260000,IF((Inputs!$B$5+C13)<=150000000,(Inputs!$B$5+C13)*0.35-15940000,IF((Inputs!$B$5+C13)<=300000000,(Inputs!$B$5+C13)*0.38-20440000,IF((Inputs!$B$5+C13)<=500000000,(Inputs!$B$5+C13)*0.4-25440000,IF((Inputs!$B$5+C13)<=1000000000,(Inputs!$B$5+C13)*0.42-35440000,(Inputs!$B$5+C13)*0.45-72340000)))))))))-(MAX(0,IF(Inputs!$B$5<=14000000,Inputs!$B$5*0.06,IF(Inputs!$B$5<=50000000,Inputs!$B$5*0.14-1260000,IF(Inputs!$B$5<=88000000,Inputs!$B$5*0.24-6260000,IF(Inputs!$B$5<=150000000,Inputs!$B$5*0.35-15940000,IF(Inputs!$B$5<=300000000,Inputs!$B$5*0.38-20440000,IF(Inputs!$B$5<=500000000,Inputs!$B$5*0.4-25440000,IF(Inputs!$B$5<=1000000000,Inputs!$B$5*0.42-35440000,Inputs!$B$5*0.45-72340000))))))))))*Inputs!$B$11)+((IF(Inputs!$B$14="Employee",MAX(0,C13-Inputs!$B$13),C13))*Inputs!$B$12) -> 2.3291389e+08 | I13: =IF(E13=0,"Undefined",H13/E13) -> 31.441285 | J13: =Inputs!$B$4*(1+Inputs!$B$8)-E13 -> 815692100 | K13: =Inputs!$B$4*(1+Inputs!$B$8)-H13 -> 5.9018611e+08
A14: 0.6 | B14: 0.99 | C14: =Inputs!$B$4*A14 -> 493860000 | D14: =Inputs!$B$9*(1-B14) -> 0.0015 | E14: =C14*D14 -> 740790 | F14: =MAX(0,Inputs!$B$10-D14) -> 0.1385 | G14: =C14*F14 -> 68399610 | H14: =(MAX(0,IF((Inputs!$B$5+C14)<=14000000,(Inputs!$B$5+C14)*0.06,IF((Inputs!$B$5+C14)<=50000000,(Inputs!$B$5+C14)*0.14-1260000,IF((Inputs!$B$5+C14)<=88000000,(Inputs!$B$5+C14)*0.24-6260000,IF((Inputs!$B$5+C14)<=150000000,(Inputs!$B$5+C14)*0.35-15940000,IF((Inputs!$B$5+C14)<=300000000,(Inputs!$B$5+C14)*0.38-20440000,IF((Inputs!$B$5+C14)<=500000000,(Inputs!$B$5+C14)*0.4-25440000,IF((Inputs!$B$5+C14)<=1000000000,(Inputs!$B$5+C14)*0.42-35440000,(Inputs!$B$5+C14)*0.45-72340000)))))))))-(MAX(0,IF(Inputs!$B$5<=14000000,Inputs!$B$5*0.06,IF(Inputs!$B$5<=50000000,Inputs!$B$5*0.14-1260000,IF(Inputs!$B$5<=88000000,Inputs!$B$5*0.24-6260000,IF(Inputs!$B$5<=150000000,Inputs!$B$5*0.35-15940000,IF(Inputs!$B$5<=300000000,Inputs!$B$5*0.38-20440000,IF(Inputs!$B$5<=500000000,Inputs!$B$5*0.4-25440000,IF(Inputs!$B$5<=1000000000,Inputs!$B$5*0.42-35440000,Inputs!$B$5*0.45-72340000)))))))))+(((MAX(0,IF((Inputs!$B$5+C14)<=14000000,(Inputs!$B$5+C14)*0.06,IF((Inputs!$B$5+C14)<=50000000,(Inputs!$B$5+C14)*0.14-1260000,IF((Inputs!$B$5+C14)<=88000000,(Inputs!$B$5+C14)*0.24-6260000,IF((Inputs!$B$5+C14)<=150000000,(Inputs!$B$5+C14)*0.35-15940000,IF((Inputs!$B$5+C14)<=300000000,(Inputs!$B$5+C14)*0.38-20440000,IF((Inputs!$B$5+C14)<=500000000,(Inputs!$B$5+C14)*0.4-25440000,IF((Inputs!$B$5+C14)<=1000000000,(Inputs!$B$5+C14)*0.42-35440000,(Inputs!$B$5+C14)*0.45-72340000)))))))))-(MAX(0,IF(Inputs!$B$5<=14000000,Inputs!$B$5*0.06,IF(Inputs!$B$5<=50000000,Inputs!$B$5*0.14-1260000,IF(Inputs!$B$5<=88000000,Inputs!$B$5*0.24-6260000,IF(Inputs!$B$5<=150000000,Inputs!$B$5*0.35-15940000,IF(Inputs!$B$5<=300000000,Inputs!$B$5*0.38-20440000,IF(Inputs!$B$5<=500000000,Inputs!$B$5*0.4-25440000,IF(Inputs!$B$5<=1000000000,Inputs!$B$5*0.42-35440000,Inputs!$B$5*0.45-72340000))))))))))*Inputs!$B$11)+((IF(Inputs!$B$14="Employee",MAX(0,C14-Inputs!$B$13),C14))*Inputs!$B$12) -> 2.3291389e+08 | I14: =IF(E14=0,"Undefined",H14/E14) -> 314.41285 | J14: =Inputs!$B$4*(1+Inputs!$B$8)-E14 -> 822359210 | K14: =Inputs!$B$4*(1+Inputs!$B$8)-H14 -> 5.9018611e+08
A15: 0.6 | B15: 1 | C15: =Inputs!$B$4*A15 -> 493860000 | D15: =Inputs!$B$9*(1-B15) -> 0 | E15: =C15*D15 -> 0 | F15: =MAX(0,Inputs!$B$10-D15) -> 0.14 | G15: =C15*F15 -> 69140400 | H15: =(MAX(0,IF((Inputs!$B$5+C15)<=14000000,(Inputs!$B$5+C15)*0.06,IF((Inputs!$B$5+C15)<=50000000,(Inputs!$B$5+C15)*0.14-1260000,IF((Inputs!$B$5+C15)<=88000000,(Inputs!$B$5+C15)*0.24-6260000,IF((Inputs!$B$5+C15)<=150000000,(Inputs!$B$5+C15)*0.35-15940000,IF((Inputs!$B$5+C15)<=300000000,(Inputs!$B$5+C15)*0.38-20440000,IF((Inputs!$B$5+C15)<=500000000,(Inputs!$B$5+C15)*0.4-25440000,IF((Inputs!$B$5+C15)<=1000000000,(Inputs!$B$5+C15)*0.42-35440000,(Inputs!$B$5+C15)*0.45-72340000)))))))))-(MAX(0,IF(Inputs!$B$5<=14000000,Inputs!$B$5*0.06,IF(Inputs!$B$5<=50000000,Inputs!$B$5*0.14-1260000,IF(Inputs!$B$5<=88000000,Inputs!$B$5*0.24-6260000,IF(Inputs!$B$5<=150000000,Inputs!$B$5*0.35-15940000,IF(Inputs!$B$5<=300000000,Inputs!$B$5*0.38-20440000,IF(Inputs!$B$5<=500000000,Inputs!$B$5*0.4-25440000,IF(Inputs!$B$5<=1000000000,Inputs!$B$5*0.42-35440000,Inputs!$B$5*0.45-72340000)))))))))+(((MAX(0,IF((Inputs!$B$5+C15)<=14000000,(Inputs!$B$5+C15)*0.06,IF((Inputs!$B$5+C15)<=50000000,(Inputs!$B$5+C15)*0.14-1260000,IF((Inputs!$B$5+C15)<=88000000,(Inputs!$B$5+C15)*0.24-6260000,IF((Inputs!$B$5+C15)<=150000000,(Inputs!$B$5+C15)*0.35-15940000,IF((Inputs!$B$5+C15)<=300000000,(Inputs!$B$5+C15)*0.38-20440000,IF((Inputs!$B$5+C15)<=500000000,(Inputs!$B$5+C15)*0.4-25440000,IF((Inputs!$B$5+C15)<=1000000000,(Inputs!$B$5+C15)*0.42-35440000,(Inputs!$B$5+C15)*0.45-72340000)))))))))-(MAX(0,IF(Inputs!$B$5<=14000000,Inputs!$B$5*0.06,IF(Inputs!$B$5<=50000000,Inputs!$B$5*0.14-1260000,IF(Inputs!$B$5<=88000000,Inputs!$B$5*0.24-6260000,IF(Inputs!$B$5<=150000000,Inputs!$B$5*0.35-15940000,IF(Inputs!$B$5<=300000000,Inputs!$B$5*0.38-20440000,IF(Inputs!$B$5<=500000000,Inputs!$B$5*0.4-25440000,IF(Inputs!$B$5<=1000000000,Inputs!$B$5*0.42-35440000,Inputs!$B$5*0.45-72340000))))))))))*Inputs!$B$11)+((IF(Inputs!$B$14="Employee",MAX(0,C15-Inputs!$B$13),C15))*Inputs!$B$12) -> 2.3291389e+08 | I15: =IF(E15=0,"Undefined",H15/E15) -> Undefined | J15: =Inputs!$B$4*(1+Inputs!$B$8)-E15 -> 823100000 | K15: =Inputs!$B$4*(1+Inputs!$B$8)-H15 -> 5.9018611e+08
... A39: 1 | B39: 1 | C39: =Inputs!$B$4*A39 -> 823100000 | D39: =Inputs!$B$9*(1-B39) -> 0 | E39: =C39*D39 -> 0 | F39: =MAX(0,Inputs!$B$10-D39) -> 0.14 | G39: =C39*F39 -> 115234000 | H39: =(MAX(0,IF((Inputs!$B$5+C39)<=14000000,(Inputs!$B$5+C39)*0.06,IF((Inputs!$B$5+C39)<=50000000,(Inputs!$B$5+C39)*0.14-1260000,IF((Inputs!$B$5+C39)<=88000000,(Inputs!$B$5+C39)*0.24-6260000,IF((Inputs!$B$5+C39)<=150000000,(Inputs!$B$5+C39)*0.35-15940000,IF((Inputs!$B$5+C39)<=300000000,(Inputs!$B$5+C39)*0.38-20440000,IF((Inputs!$B$5+C39)<=500000000,(Inputs!$B$5+C39)*0.4-25440000,IF((Inputs!$B$5+C39)<=1000000000,(Inputs!$B$5+C39)*0.42-35440000,(Inputs!$B$5+C39)*0.45-72340000)))))))))-(MAX(0,IF(Inputs!$B$5<=14000000,Inputs!$B$5*0.06,IF(Inputs!$B$5<=50000000,Inputs!$B$5*0.14-1260000,IF(Inputs!$B$5<=88000000,Inputs!$B$5*0.24-6260000,IF(Inputs!$B$5<=150000000,Inputs!$B$5*0.35-15940000,IF(Inputs!$B$5<=300000000,Inputs!$B$5*0.38-20440000,IF(Inputs!$B$5<=500000000,Inputs!$B$5*0.4-25440000,IF(Inputs!$B$5<=1000000000,Inputs!$B$5*0.42-35440000,Inputs!$B$5*0.45-72340000)))))))))+(((MAX(0,IF((Inputs!$B$5+C39)<=14000000,(Inputs!$B$5+C39)*0.06,IF((Inputs!$B$5+C39)<=50000000,(Inputs!$B$5+C39)*0.14-1260000,IF((Inputs!$B$5+C39)<=88000000,(Inputs!$B$5+C39)*0.24-6260000,IF((Inputs!$B$5+C39)<=150000000,(Inputs!$B$5+C39)*0.35-15940000,IF((Inputs!$B$5+C39)<=300000000,(Inputs!$B$5+C39)*0.38-20440000,IF((Inputs!$B$5+C39)<=500000000,(Inputs!$B$5+C39)*0.4-25440000,IF((Inputs!$B$5+C39)<=1000000000,(Inputs!$B$5+C39)*0.42-35440000,(Inputs!$B$5+C39)*0.45-72340000)))))))))-(MAX(0,IF(Inputs!$B$5<=14000000,Inputs!$B$5*0.06,IF(Inputs!$B$5<=50000000,Inputs!$B$5*0.14-1260000,IF(Inputs!$B$5<=88000000,Inputs!$B$5*0.24-6260000,IF(Inputs!$B$5<=150000000,Inputs!$B$5*0.35-15940000,IF(Inputs!$B$5<=300000000,Inputs!$B$5*0.38-20440000,IF(Inputs!$B$5<=500000000,Inputs!$B$5*0.4-25440000,IF(Inputs!$B$5<=1000000000,Inputs!$B$5*0.42-35440000,Inputs!$B$5*0.45-72340000))))))))))*Inputs!$B$11)+((IF(Inputs!$B$14="Employee",MAX(0,C39-Inputs!$B$13),C39))*Inputs!$B$12) -> 411803154 | I39: =IF(E39=0,"Undefined",H39/E39) -> Undefined | J39: =Inputs!$B$4*(1+Inputs!$B$8)-E39 -> 823100000 | K39: =Inputs!$B$4*(1+Inputs!$B$8)-H39 -> 411296846

Sheet Sources
A1: Sources / 근거
A3: Topic | B3: URL | C3: Note
A4: IRS ROC treatment | B4: https://www.irs.gov/taxtopics/tc404 | C4: ROC/nondividend distribution basis reduction reference.
A5: Korea individual tax | B5: https://taxsummaries.pwc.com/republic-of-korea/individual/taxes-on-personal-income | C5: Income tax brackets and local tax reference.
A6: NHIS contribution | B6: https://www.nhis.or.kr/english/wbheaa02500m01.do | C6: Health insurance and LTC reference.
A7: User model | B7: Conversation-provided logic | C7: KR differential withholding = MAX(0,14%-US tax rate).
A8: Workbook | B8: Formula-driven | C8: Edit Inputs sheet to update all outputs.
